tryton_filestore_cellar.py
tryton_filestore_cellar-0.1.0.dist-info/LICENSE
tryton_filestore_cellar-0.1.0.dist-info/METADATA
tryton_filestore_cellar-0.1.0.dist-info/WHEEL
tryton_filestore_cellar-0.1.0.dist-info/top_level.txt
tryton_filestore_cellar-0.1.0.dist-info/RECORD
