Metadata-Version: 2.1
Name: tryton-filestore-cellar
Version: 0.1.0
Summary: Store Tryton files on Cellar Storage Service
Home-page: https://pypi.org/project/tryton-filestore-cellar/
Download-URL: https://downloads.tryton.org/tryton-filestore-cellar/
Author: Tryton
Author-email: foundation@tryton.org
License: GPL-3
Project-URL: Bug Tracker, https://bugs.tryton.org/tryton-filestore-cellar
Project-URL: Forum, https://discuss.tryton.org/tags/filestore-cellar
Project-URL: Source Code, https://code.tryton.org/tryton-filestore-cellar
Keywords: tryton clever cloud cellar storage
Platform: Posix; MacOS X; Windows
Classifier: Framework :: Tryton
Classifier: Intended Audience :: Developers
Classifier: License :: OSI Approved :: GNU General Public License (GPL)
Classifier: Operating System :: OS Independent
Classifier: Programming Language :: Python :: 3
Classifier: Topic :: Internet
License-File: LICENSE
Requires-Dist: boto
Requires-Dist: trytond >6.0
